[{"__type__":"cc.SpriteFrame","content":{"name":"C_UI_touxiangkuang_hong","texture":"1bf14a76a","rect":[643,185,66,66],"offset":[0,0],"originalSize":[66,66],"capInsets":[22,22,22,22]}},{"__type__":"cc.SpriteFrame","content":{"name":"C_image_QR_code_01","texture":"116c69945","rect":[3,3,80,80],"offset":[0,0],"originalSize":[80,80],"capInsets":[0,0,0,0]}},{"__type__":"cc.SpriteFrame","content":{"name":"C_tag_icon_VIP_01","texture":"1bf14a76a","rect":[932,558,29,40],"offset":[0.5,0],"originalSize":[30,40],"capInsets":[0,0,0,0]}},{"__type__":"cc.SpriteFrame","content":{"name":"C_icon_80_logo_01","texture":"116c69945","rect":[3,89,80,80],"offset":[0,0],"originalSize":[80,80],"capInsets":[0,0,0,0]}},{"__type__":"cc.SpriteFrame","content":{"name":"C_UI_touxiangkuang_zhengchang","texture":"1bf14a76a","rect":[643,257,66,66],"offset":[0,0],"originalSize":[66,66],"capInsets":[22,22,22,22]}},[{"__type__":"cc.Prefab","_name":"ShareLogoBar","data":{"__id__":1}},{"__type__":"cc.Node","_name":"ShareLogoBar","_children":[{"__id__":2},{"__id__":3},{"__id__":5},{"__id__":6},{"__id__":8}],"_components":[{"__type__":"cc.Widget","node":{"__id__":1},"_alignFlags":20},{"__type__":"7c7e9T+SeRI6JIlsMs5C5hT","node":{"__id__":1},"mErWeiMaSprite":{"__id__":7},"m_spriteFrames":[{"__uuid__":"d9MC2DM6hN7LojIFqkXEoQ"},{"__uuid__":"37a/PKwetEKZdJNncETJf2"}],"m_preLink_myHeadComp":{"__id__":9}}],"_prefab":{"__type__":"cc.PrefabInfo","root":{"__id__":1},"asset":{"__uuid__":"5b9uN/lZhCY7GxjL6rPii2"},"fileId":"aftCr6gChGcI3C9xbasgV5"},"_contentSize":{"__type__":"cc.Size","width":640,"height":200},"_anchorPoint":{"__type__":"cc.Vec2","x":0.5},"_trs":{"__type__":"TypedArray","ctor":"Float64Array","array":[320,0,0,0,0,0,1,1,1,1]}},{"__type__":"cc.Node","_name":"New Sprite(Splash)","_parent":{"__id__":1},"_components":[{"__type__":"cc.Sprite","node":{"__id__":2},"_materials":[{"__uuid__":"ecpdLyjvZBwrvm+cedCcQy"}],"_spriteFrame":{"__uuid__":"cdvxuFYRpBW5oXvDdw+KWE"},"_type":1,"_sizeMode":0},{"__type__":"cc.Widget","node":{"__id__":2},"_alignFlags":44,"_originalWidth":100}],"_prefab":{"__type__":"cc.PrefabInfo","root":{"__id__":1},"asset":{"__uuid__":"5b9uN/lZhCY7GxjL6rPii2"},"fileId":"658HKWt2VPUYkinsuDUH6Z"},"_opacity":77,"_color":{"__type__":"cc.Color"},"_contentSize":{"__type__":"cc.Size","width":640,"height":90},"_trs":{"__type__":"TypedArray","ctor":"Float64Array","array":[0,45,0,0,0,0,1,1,1,1]}},{"__type__":"cc.Node","_name":"New Label","_parent":{"__id__":1},"_children":[{"__id__":4}],"_components":[{"__type__":"cc.Widget","node":{"__id__":3},"_alignFlags":12,"_left":110,"_bottom":41.541}],"_prefab":{"__type__":"cc.PrefabInfo","root":{"__id__":1},"asset":{"__uuid__":"5b9uN/lZhCY7GxjL6rPii2"},"fileId":"15WT7DcQxD96D2pw20XnAt"},"_contentSize":{"__type__":"cc.Size","width":115.735,"height":30},"_anchorPoint":{"__type__":"cc.Vec2","y":0.5},"_trs":{"__type__":"TypedArray","ctor":"Float64Array","array":[-210,56.541,0,0,0,0,1,1,1,1]}},{"__type__":"cc.Node","_name":"label","_parent":{"__id__":3},"_components":[{"__type__":"cc.Label","node":{"__id__":4},"_materials":[{"__uuid__":"ecpdLyjvZBwrvm+cedCcQy"}],"_string":"天天象棋","_N$string":"天天象棋","_fontSize":28,"_lineHeight":30,"_N$verticalAlign":1,"_N$cacheMode":2}],"_prefab":{"__type__":"cc.PrefabInfo","root":{"__id__":1},"asset":{"__uuid__":"5b9uN/lZhCY7GxjL6rPii2"},"fileId":"78K83INvFAN6f+zx6/VG9u"},"_color":{"__type__":"cc.Color","r":244,"g":233,"b":216},"_contentSize":{"__type__":"cc.Size","width":112,"height":30},"_anchorPoint":{"__type__":"cc.Vec2","y":0.5},"_trs":{"__type__":"TypedArray","ctor":"Float64Array","array":[0,0,0,0,0,0,1,1,1,1]}},{"__type__":"cc.Node","_name":"C_Head_Default","_parent":{"__id__":1},"_components":[{"__type__":"cc.Sprite","node":{"__id__":5},"_materials":[{"__uuid__":"ecpdLyjvZBwrvm+cedCcQy"}],"_spriteFrame":{"__uuid__":"48owNqzQlIh7IHjhoneG4v"}},{"__type__":"cc.Widget","node":{"__id__":5},"_alignFlags":12,"_left":21,"_bottom":17}],"_prefab":{"__type__":"cc.PrefabInfo","root":{"__id__":1},"asset":{"__uuid__":"5b9uN/lZhCY7GxjL6rPii2"},"fileId":"b9JZytZUhAer8mxh2c37RN"},"_contentSize":{"__type__":"cc.Size","width":80,"height":80},"_trs":{"__type__":"TypedArray","ctor":"Float64Array","array":[-259,57,0,0,0,0,1,1,1,1]}},{"__type__":"cc.Node","_name":"C_Head_Empty","_parent":{"__id__":1},"_components":[{"__id__":7},{"__type__":"cc.Widget","node":{"__id__":6},"_alignFlags":36,"_right":19.73599999999999,"_bottom":18}],"_prefab":{"__type__":"cc.PrefabInfo","root":{"__id__":1},"asset":{"__uuid__":"5b9uN/lZhCY7GxjL6rPii2"},"fileId":"60kgSdxmxLI4tkBUVotdJz"},"_contentSize":{"__type__":"cc.Size","width":80,"height":80},"_trs":{"__type__":"TypedArray","ctor":"Float64Array","array":[260.264,58,0,0,0,0,1,1,1,1]}},{"__type__":"cc.Sprite","node":{"__id__":6},"_materials":[{"__uuid__":"ecpdLyjvZBwrvm+cedCcQy"}],"_spriteFrame":{"__uuid__":"37a/PKwetEKZdJNncETJf2"},"_sizeMode":0},{"__type__":"cc.Node","_name":"C_Head","_parent":{"__id__":1},"_children":[],"_components":[{"__id__":9},{"__type__":"cc.Widget","node":{"__id__":8},"_alignFlags":36,"_right":19.73599999999999,"_bottom":18}],"_prefab":{"__type__":"cc.PrefabInfo","root":{"__id__":1},"asset":{"__uuid__":"5b9uN/lZhCY7GxjL6rPii2"},"fileId":"b68ofwVaJBH5W/2Ky6B60Y"},"_contentSize":{"__type__":"cc.Size","width":80,"height":80},"_trs":{"__type__":"TypedArray","ctor":"Float64Array","array":[260.264,58,0,0,0,0,1,1,1,1]}},{"__type__":"adc58oy0HlAPJS/vDOC0i9l","node":{"__id__":8},"_N$targetPrefab":{"__uuid__":"14c/kzJ8BDmaUQZNEpRHGw"}}],{"__type__":"cc.SpriteFrame","content":{"name":"C_UI_touxiangkuang_hei","texture":"1bf14a76a","rect":[643,329,66,66],"offset":[0,0],"originalSize":[66,66],"capInsets":[22,22,22,22]}},{"__type__":"cc.SpriteFrame","content":{"name":"C_tag_icon_dashi_01","texture":"18fbe0a3e","rect":[841,321,40,23],"offset":[0,0.5],"originalSize":[40,24],"capInsets":[0,0,0,0]}},{"__type__":"cc.SpriteFrame","content":{"name":"C_tag_icon_Wahat_01","texture":"18fbe0a3e","rect":[887,319,30,25],"offset":[0,-5.5],"originalSize":[30,40],"capInsets":[0,0,0,0]}},{"__type__":"cc.SpriteFrame","content":{"name":"C_tag_icon_teda_01","texture":"18fbe0a3e","rect":[779,640,40,23],"offset":[0,0.5],"originalSize":[40,24],"capInsets":[0,0,0,0]}},{"__type__":"cc.SpriteFrame","content":{"name":"C_tag_icon_xinyong_01","texture":"18fbe0a3e","rect":[761,669,40,23],"offset":[0,0.5],"originalSize":[40,24],"capInsets":[0,0,0,0]}},{"__type__":"cc.SpriteFrame","content":{"name":"C_Head_moren","texture":"1bf14a76a","rect":[806,895,120,120],"offset":[0,0],"originalSize":[120,120],"capInsets":[0,0,0,0]}},{"__type__":"cc.SpriteFrame","content":{"name":"C_frame_Whiteboard_corner_20_2","texture":"18fbe0a3e","rect":[763,354,50,30],"offset":[0,0],"originalSize":[50,30],"capInsets":[24,22,24,0]}},{"__type__":"cc.SpriteFrame","content":{"name":"C_tag_icon_shiming_01","texture":"18fbe0a3e","rect":[825,640,40,23],"offset":[0,0.5],"originalSize":[40,24],"capInsets":[0,0,0,0]}},{"__type__":"cc.SpriteFrame","content":{"name":"Share_erweima_WX","texture":"116c69945","rect":[89,3,80,80],"offset":[0,0],"originalSize":[80,80],"capInsets":[0,0,0,0]}},{"__type__":"cc.SpriteFrame","content":{"name":"C_tag_icon_zhuanye_01","texture":"18fbe0a3e","rect":[846,481,40,23],"offset":[0,0.5],"originalSize":[40,24],"capInsets":[0,0,0,0]}},{"__type__":"cc.SpriteFrame","content":{"name":"C_Head_Empty","texture":"1bf14a76a","rect":[841,758,120,120],"offset":[0,0],"originalSize":[120,120],"capInsets":[0,0,0,0]}}]